.gitignore
benchmarks/__init__.py
benchmarks/bench_encodings.py
benchmarks/bench_gc.py
benchmarks/bench_large_json.py
benchmarks/bench_library_size.py
benchmarks/bench_structs.py
benchmarks/bench_validation/__init__.py
benchmarks/bench_validation/__main__.py
benchmarks/bench_validation/bench_cattrs.py
benchmarks/bench_validation/bench_mashumaro.py
benchmarks/bench_validation/bench_msgspec.py
benchmarks/bench_validation/bench_pydantic.py
benchmarks/bench_validation/runner.py
benchmarks/generate_data.py
msgspec/__init__.py
msgspec/__init__.pyi
msgspec/_core.c
msgspec/_core.cpython-313-darwin.so
msgspec/_json_schema.py
msgspec/_utils.py
msgspec/_version.py
msgspec/atof.h
msgspec/atof_consts.h
msgspec/common.h
msgspec/inspect.py
msgspec/itoa.h
msgspec/json.py
msgspec/json.pyi
msgspec/msgpack.py
msgspec/msgpack.pyi
msgspec/py.typed
msgspec/ryu.h
msgspec/structs.py
msgspec/structs.pyi
msgspec/toml.py
msgspec/yaml.py
msgspec_python313_pre-0.19.3.dist-info/METADATA
msgspec_python313_pre-0.19.3.dist-info/WHEEL
msgspec_python313_pre-0.19.3.dist-info/entry_points.txt
msgspec_python313_pre-0.19.3.dist-info/licenses/LICENSE
msgspec_python313_pre-0.19.3.dist-info/RECORD
