Metadata-Version: 2.1
Name: msgspec-python313-pre
Version: 0.19.3
Summary: A fast serialization and validation library, with builtin support for JSON, MessagePack, YAML, and TOML.
Keywords: JSON msgpack MessagePack TOML YAML serialization validation schema
Author-Email: Jim Crist-Harif <jcristharif@gmail.com>
Maintainer-Email: Jim Crist-Harif <jcristharif@gmail.com>
License: BSD
Classifier: Development Status :: 4 - Beta
Classifier: License :: OSI Approved :: BSD License
Classifier: Programming Language :: Python :: 3.10
Classifier: Programming Language :: Python :: 3.11
Classifier: Programming Language :: Python :: 3.12
Classifier: Programming Language :: Python :: 3.13
Classifier: Programming Language :: Python :: 3.9
Project-URL: Homepage, https://jcristharif.com/msgspec/
Project-URL: Documentation, https://jcristharif.com/msgspec/
Project-URL: Source, https://github.com/jcrist/msgspec/
Project-URL: Issue Tracker, https://github.com/jcrist/msgspec/issues
Requires-Python: >=3.9
Requires-Dist: setuptools>=75.3.0
Provides-Extra: yaml
Requires-Dist: pyyaml; extra == "yaml"
Provides-Extra: toml
Requires-Dist: tomli; python_version < "3.11" and extra == "toml"
Requires-Dist: tomli_w; extra == "toml"
Provides-Extra: doc
Requires-Dist: furo; extra == "doc"
Requires-Dist: ipython; extra == "doc"
Requires-Dist: sphinx; extra == "doc"
Requires-Dist: sphinx-copybutton; extra == "doc"
Requires-Dist: sphinx-design; extra == "doc"
Provides-Extra: test
Requires-Dist: attrs; extra == "test"
Requires-Dist: msgpack; extra == "test"
Requires-Dist: mypy; extra == "test"
Requires-Dist: pyright; extra == "test"
Requires-Dist: pytest; extra == "test"
Requires-Dist: pyyaml; extra == "test"
Requires-Dist: tomli; python_version < "3.11" and extra == "test"
Requires-Dist: tomli_w; extra == "test"
Provides-Extra: dev
Requires-Dist: attrs; extra == "dev"
Requires-Dist: coverage; extra == "dev"
Requires-Dist: furo; extra == "dev"
Requires-Dist: gcovr; extra == "dev"
Requires-Dist: ipython; extra == "dev"
Requires-Dist: msgpack; extra == "dev"
Requires-Dist: mypy; extra == "dev"
Requires-Dist: pre-commit; extra == "dev"
Requires-Dist: pyright; extra == "dev"
Requires-Dist: pytest; extra == "dev"
Requires-Dist: pyyaml; extra == "dev"
Requires-Dist: sphinx; extra == "dev"
Requires-Dist: sphinx-copybutton; extra == "dev"
Requires-Dist: sphinx-design; extra == "dev"
Requires-Dist: tomli; python_version < "3.11" and extra == "dev"
Requires-Dist: tomli_w; extra == "dev"
